pickledict/__init__.py
pickledict/dict.py
pickledict/list.py
pickledict-1.0.2.dist-info/METADATA
pickledict-1.0.2.dist-info/WHEEL
pickledict-1.0.2.dist-info/top_level.txt
pickledict-1.0.2.dist-info/RECORD
