Metadata-Version: 2.1
Name: pickledict
Version: 1.0.2
Summary: Auto-saving dicts and lists
Home-page: https://github.com/driazati/pickledict
Author: driazati
Author-email: email@example.com
License: UNKNOWN
Platform: UNKNOWN
Classifier: Programming Language :: Python :: 3
Classifier: License :: OSI Approved :: MIT License
Classifier: Operating System :: OS Independent
Requires-Python: >=3.6
